{
    "users": [
      {
        "id": "u1",
        "password": "$2b$10$xOgGBAkm2RKGGh43ij1Or.UJv9xU5VXyleEA9aWu8UR9SxiWbQpxC",
        "name": "didof"
      },
      {
        "id": "u2",
        "password": "$2b$10$xOgGBAkm2RKGGh43ij1Or.UJv9xU5VXyleEA9aWu8UR9SxiWbQpxC",
        "name": "Kelly"
      },
      {
        "id": "u3",
        "password": "$2b$10$xOgGBAkm2RKGGh43ij1Or.UJv9xU5VXyleEA9aWu8UR9SxiWbQpxC",
        "name": "Byte"
      }
    ],
    "posts": [
      {
        "id": "p1",
        "title": "Trying to build Next.js",
        "content": "Lot of work!",
        "authorId": "u1",
        "draft": false
      },
      {
        "id": "p2",
        "title": "Merging Micro-FrontEnd in SSR",
        "content": "I don't have the slightest idea",
        "authorId": "u1",
        "draft": true
      }
    ]
  }